jupyter_nbextensions_configurator/__init__.py
jupyter_nbextensions_configurator/application.py
jupyter_nbextensions_configurator/static/nbextensions_configurator/icon.png
jupyter_nbextensions_configurator/static/nbextensions_configurator/kse_components.js
jupyter_nbextensions_configurator/static/nbextensions_configurator/main.css
jupyter_nbextensions_configurator/static/nbextensions_configurator/main.js
jupyter_nbextensions_configurator/static/nbextensions_configurator/quickhelp_shim.js
jupyter_nbextensions_configurator/static/nbextensions_configurator/readme.md
jupyter_nbextensions_configurator/static/nbextensions_configurator/config_menu/config_menu.yaml
jupyter_nbextensions_configurator/static/nbextensions_configurator/config_menu/icon.png
jupyter_nbextensions_configurator/static/nbextensions_configurator/config_menu/main.js
jupyter_nbextensions_configurator/static/nbextensions_configurator/render/render.js
jupyter_nbextensions_configurator/static/nbextensions_configurator/render/rendermd.css
jupyter_nbextensions_configurator/static/nbextensions_configurator/render/video_play.svg
jupyter_nbextensions_configurator/static/nbextensions_configurator/tree_tab/icon.png
jupyter_nbextensions_configurator/static/nbextensions_configurator/tree_tab/main.js
jupyter_nbextensions_configurator/static/nbextensions_configurator/tree_tab/readme.md
jupyter_nbextensions_configurator/static/nbextensions_configurator/tree_tab/tree_tab.yaml
jupyter_nbextensions_configurator/templates/nbextensions_configurator.html
jupyter_nbextensions_configurator/templates/rendermd.html
jupyter_nbextensions_configurator-0.6.2.data/data/etc/jupyter/jupyter_notebook_config.d/jupyter_nbextensions_configurator.json
jupyter_nbextensions_configurator-0.6.2.data/data/etc/jupyter/nbconfig/notebook.d/jupyter_nbextensions_configurator.json
jupyter_nbextensions_configurator-0.6.2.data/data/etc/jupyter/nbconfig/tree.d/jupyter_nbextensions_configurator.json
jupyter_nbextensions_configurator-0.6.2.dist-info/LICENSE.txt
jupyter_nbextensions_configurator-0.6.2.dist-info/METADATA
jupyter_nbextensions_configurator-0.6.2.dist-info/WHEEL
jupyter_nbextensions_configurator-0.6.2.dist-info/entry_points.txt
jupyter_nbextensions_configurator-0.6.2.dist-info/top_level.txt
jupyter_nbextensions_configurator-0.6.2.dist-info/RECORD
