Metadata-Version: 2.1
Name: jupyter-nbextensions-configurator
Version: 0.6.2
Summary: jupyter serverextension providing configuration interfaces for nbextensions.
Home-page: https://github.com/jupyter-contrib/jupyter_nbextensions_configurator
Download-URL: https://github.com/jupyter-contrib/jupyter_nbextensions_configurator/tarball/0.6.2
Author: jcb91, jupyter-contrib developers
Author-email: joshuacookebarnes@gmail.com
License: BSD 3-clause
Keywords: Jupyter,notebook
Platform: any
Classifier: Intended Audience :: End Users/Desktop
Classifier: Intended Audience :: Science/Research
Classifier: License :: OSI Approved :: BSD License
Classifier: Natural Language :: English
Classifier: Operating System :: OS Independent
Classifier: Programming Language :: JavaScript
Classifier: Programming Language :: Python
Classifier: Programming Language :: Python :: 3
Classifier: Topic :: Utilities
License-File: LICENSE.txt
Requires-Dist: jupyter-contrib-core (>=0.3.3)
Requires-Dist: jupyter-core
Requires-Dist: notebook (>=6.0)
Requires-Dist: pyyaml
Requires-Dist: tornado
Requires-Dist: traitlets
Provides-Extra: test
Requires-Dist: jupyter-contrib-core[testing_utils] ; extra == 'test'
Requires-Dist: nose ; extra == 'test'
Requires-Dist: requests ; extra == 'test'
Requires-Dist: selenium ; extra == 'test'
Requires-Dist: mock ; (python_version == "3.9") and extra == 'test'
